fritzctl/__init__.py
fritzctl/dynapi.py
fritzctl/session.py
fritzctl/ooapi/__init__.py
fritzctl/ooapi/avm_homeauto.py
fritzctl/ooapi/avm_homeplug.py
fritzctl/ooapi/base.py
fritzctl/ooapi/general_deviceconfig.py
fritzctl/ooapi/general_deviceinfo.py
fritzctl/ooapi/general_hosts.py
fritzctl/ooapi/general_time.py
fritzctl/ooapi/net_wlan_multi.py
fritzctl-1.0.0a3.dist-info/LICENSE.md
fritzctl-1.0.0a3.dist-info/METADATA
fritzctl-1.0.0a3.dist-info/WHEEL
fritzctl-1.0.0a3.dist-info/top_level.txt
fritzctl-1.0.0a3.dist-info/RECORD
